<document>
	<date>2014-11-03</date>
        <title>Apr&#232;s Assassin&#8217;s Creed, Ubisoft l&#226;che les configurations n&#233;cessaires pour faire tourner The Crew</title>
        <author>Henri</author>
        <tags_set>
                <tag>Assassin's Creed</tag>
                <tag>Hardware</tag>
                <tag>PC</tag>
                <tag>The Crew</tag>
                <tag>Ubisoft</tag>
        </tags_set>
        <categories_set>
                <category>D&#233;veloppement</category>
        </categories_set>
        <text>
                                                                                                 
         
                 The Crew  sort dans un mois, et s&#8217;annonce comme un s&#233;rieux concurrent au meilleur jeu de course arcade de l&#8217;ann&#233;e. Mais pourrez-vous le faire tourner sur PC ? 
 
 more 
 Ubisoft a plac&#233; de vraies attentes dans  The Crew  (nos  impressions ), puisque la firme entend bien en &#233;couler  deux millions d&#8217;unit&#233;s . Mais pourra-t-il tourner sur un nombre maximum de machines ? C&#8217;est en tout cas ce que pouvaient se demander les joueurs PC apr&#232;s avoir vu les  configurations pharaoniques  demand&#233;es pour faire tourner le prochain  Assassin&#8217;s Creed Unity . 
 Fort heureusement, vous n&#8217;aurez pas besoin d&#8217;une machine de guerre pour profiter de l&#8217;open-world am&#233;ricain cr&#233;&#233; par Ubi. Notez malgr&#233; tout que le jeu ne tournera que sur des OS 64 bits. 
 Configuration minimum requise 
 Syst&#232;me d&#8217;exploitation: Windows 7 SP1, Windows 8, Windows 8.1 (64bit) 
 Processeur: Intel Core2 Quad Q9300 @ 2.5 GHz ou sup&#233;rieur, AMD Athlon II X4 620 @ 2.6 GHz ou sup&#233;rieur 
 RAM: 4 Go 
 Carte graphique: NVIDIA GeForce GTX 260 ou AMD Radeon HD4870 (512MB VRAM avec Shader Model 4.0 ou sup&#233;rieur) 
 Configuration recommand&#233;e 
 Syst&#232;me d&#8217;exploitation: Windows 7 SP1, Windows 8, Windows 8.1 (64bit) 
 Processeur: Intel Core i5 750 @ 2.66 GHz ou sup&#233;rieur, AMD Phenom II X4 940 @ 3.0 GHz ou sup&#233;rieur 
 RAM: 8 Go 
 Carte graphique: NVIDIA GeForce GTX580 ou AMD Radeon HD6870 (1024MB VRAM avec Shader Model 5.0 ou sup&#233;rieur) 
 Configuration optimale 
 Syst&#232;me d&#8217;exploitation: Windows 7 SP1, Windows 8, Windows 8.1 (64bit) 
 Processeur : Intel Core i7-2600K @ 3.4 GHz or AMD FX-8150 @ 3.6 GHz  
 RAM : 8GB 
 Carte Graphique : NVIDIA GeForce GTX670 or AMD Radeon 7870 (2048MB VRAM ) 
 Vous &#234;tes pr&#233;venus ! 
         
 
                                                                                                         
                                                                                                                                                                                                 
        </text>
</document>
