<document>
	<date>2012-01-27</date>
        <title>Non, The Witcher 3 n&#8217;a pas &#233;t&#233; officialis&#233; !</title>
        <author>R&#233;dacteur Invit&#233;</author>
        <tags_set>
                <tag>CD Projekt Red</tag>
                <tag>PC</tag>
                <tag>The Witcher 2</tag>
                <tag>The Witcher 3</tag>
                <tag>Xbox 360</tag>
        </tags_set>
        <categories_set>
                <category>PC</category>
        </categories_set>
        <text>
                                                                                                 
         
                 Selon diverses rumeurs,  CD Projekt RED  aurait officialis&#233; il y a quelques heures de cela via sa page Facebook  The Witcher 3 , qui aurait alors &#233;t&#233; pr&#233;vu pour d&#233;bouler sur pas moins de 3 plates-formes :  PC, Playstation 3 et Xbox 360 . Dommage, il ne semble s&#8217;agir que d&#8217;un vulgaire fake. Pour autant, le studio de d&#233;veloppement a depuis confirm&#233; que la version Xbox 360 de  The Witcher 2  serait disponible le 17 avril prochain, soit le m&#234;me jour que la version PC Enhanced Edition. 
 
 more 
 
         
 Source 
                                                                                                         
                                                                                                                                                                                                 
        </text>
</document>
