<document>
	<date>2013-05-07</date>
        <title>R&#233;sultats du concours Tomb Raider</title>
        <author>Quantic</author>
        <tags_set>
                <tag>concours</tag>
                <tag>tomb raider</tag>
                <tag>r&#233;sultats</tag>
                <tag>gagnants</tag>
                <tag>square enix</tag>
        </tags_set>
        <categories_set>
                <category>Concours</category>
        </categories_set>
        <text>
 
 
 Vous &#233;tiez nombreux &#224; les r&#233;clamer, voici donc les r&#233;sultats du  concours Tomb Raider , organis&#233; en partenariat avec Square Enix. 
 
 Comme d'habitude, les gagnants ont &#233;t&#233; tir&#233;s au sort avec  Random.org . 
 - 1 Survival Edition PS3 et une casquette Tomb Raider : 
 Sheldonbxl  (via son commentaire sur le site) 
 -  1 &#233;dition Combat Strike de Tomb Raider sur PS3  : 
 Ang&#233;lique Lailler  (via Facebook) 
 -  1 &#233;dition Combat Strike de Tomb Raider sur PC  :  
 Lumo  (via son commentaire sur le site) 
 Delphine Pierlot  (via Facebook) 
 -  1 Casquette Tomb Raider : 
 Ticlain  (via Twitter) 
 Nous invitons les gagnants  &#224; nous contacter au plus vite  en nous donnant leur adresse postale compl&#232;te.  A la r&#233;ception du lot, une petite photo post&#233;e via Twitter ou sur notre page Facebook nous ferait tr&#232;s plaisir ;-). 
 
 
 
 
        </text>
</document>
