<document>
	<date>2014-05-03</date>
        <title>[ILLUSTRATION] Sur le dos d&#8217;un Yoshi&#8230;</title>
        <author>JohnCouscous</author>
        <tags_set>
                <tag>caricature</tag>
                <tag>dessin</tag>
                <tag>dino</tag>
                <tag>dodo</tag>
                <tag>illustration</tag>
                <tag>Island</tag>
                <tag>nintendo</tag>
                <tag>oeuf</tag>
                <tag>skuld</tag>
                <tag>yoshi</tag>
        </tags_set>
        <categories_set>
                <category>3DS</category>
                <category>A la une</category>
                <category>Humour</category>
                <category>Jeux Vid&#233;o</category>
        </categories_set>
        <text>
                 
                                                                                         
                                                                                         
                                                                                 Apr&#232;s  une premi&#232;re illustration  sur  Donkey Kong Country : Tropical Freeze , on reste dans l&#8217; univers de Nintendo  avec  un nouveau dessin, mais sur 3DS  ce coup-ci. 
 
 Plus r&#233;cemment, j&#8217;ai pu m&#8217;aventurer dans  Yoshi&#8217;s New Island sur 3DS  que  j&#8217;ai eu du mal &#224; appr&#233;cier . 
 C&#8217;est pourquoi dans cette illustration, on se rend compte que ma  caricature en &#171;&#160;b&#233;b&#233; couscous&#160;&#187;  s&#8217;ennuie un peu, au d&#233;triment du joli dinosaure vert. 
 Vous l&#8217;aurez peut-&#234;tre reconnu,  cette oeuvre vient une nouvelle fois de  @SoSkuld , dont je vous invite &#224; (re)d&#233;couvrir  ses jolies illustrations  &#128521; 
 &#192; tr&#232;s vite pour  une prochaine illu !  &#128521; 
 
                                                                                         
                                                                                         
                                                                                                                 
                                         
        </text>
</document>
