<document>
	<date>2013-11-07</date>
        <title>#INTERCLIMA2013 : Le module EnOcean pour Zipabox prsent sur le stand Vitec</title>
        <author> Laurent </author>
        <tags_set>
                <tag>enocean</tag>
                <tag>interclima</tag>
                <tag>interclima+elec</tag>
                <tag>vitec</tag>
                <tag>zipabox</tag>
                <tag>zipato</tag>
        </tags_set>
        <categories_set>
                <category>Domotique</category>
        </categories_set>
        <text>
                                                         Si vous nous suivez sur Twitter, vous avez pu voiren exclusivite mondiale la photo du module EnOcean pour la Zipabox Zipato Interclima Vitec Le module dextension  EnOcean modules dextension RF 433MHz ZigBee EnOcean Pour linstant seuls quelques peripheriques  EnOcean GEE679894 T2S10020032 HOP2473207 VITA1002 T2S10020033 VEREOSC Cette liste est bien evidemment susceptible devoluer en fonction des besoins et des demandes dutilisateurs. Pour linstant le module  EnOcean Zipabox phase  Simple Share Buttons Adder (5.6) simplesharebuttons.com  
 Ces sujets pourraient vous interesser aussi: Aucune proposition. END .entry-content  
        </text>
</document>
