<document>
	<date>2014-10-11</date>
        <title> </title>
        <author>JulSa_</author>
        <tags_set>
                <tag>coca cola</tag>
                <tag>just dance</tag>
                <tag>Just Dance Now</tag>
                <tag>Mobile</tag>
                <tag>Twins</tag>
                <tag>Ubisoft</tag>
        </tags_set>
        <categories_set>
                <category>Actualit&#233;s</category>
                <category>Jeux Vid&#233;o</category>
        </categories_set>
        <text>  Apr&#232;s le succ&#232;s du jeu vid&#233;o  Just Dance  sur console, vous pouvez maintenant&#160; bouger&#160; n&#8217;importe o&#249; gr&#226;ce &#224; la version mobile,&#160; Just Dance Now  ! Ubisoft&#160;en partenariat avec&#160; Coca-Cola  propose ce jeu en t&#233;l&#233;chargement en scannant le  QR code visible  sur&#160;25 millions de  canettes  de 250 ml de Coca-Cola, Coca-Cola Light et Coca-Cola Z&#233;ro. La campagne nomm&#233;e,  Le mouvement, c&#8217;est le bonheur  propose aux jeunes de danser sur le nouvel hymne de la boisson,  Find Your Move . Sur le  jeu mobile  vous aurez acc&#232;s &#224; cette chanson  gratuitement , mais aussi au titre  Movement is Happiness (Find Your Thing)&#160; des&#160; Twins  et le morceau  The World&#160;Yours &#160;de  David Corey .&#160;Puis des ajouts de  musique&#160; auront ensuite lieu chaque semaine.&#160;Pour le&#160;lancement du jeu,  Just Dance Now , les deux fr&#232;res du duo,&#160;les  Twins  sont venus  danser  avec les passants de la  gare Paris Saint-Lazare  ! &#160;     Article sponsoris&#233;. 
        </text>
</document>
